[
  {
    "platform": "Spotify",
    "timestamp": "2025-09-24T07:35:12.492Z",
    "content": "MEG の「N07B」を聴きました",
    "url": "https://open.spotify.com/track/3xnGi8Wn71hHr5pGRmmagF"
  },
  {
    "platform": "Spotify",
    "timestamp": "2025-09-24T03:13:10.164Z",
    "content": "Fujii Kaze の「Forever Young」を聴きました",
    "url": "https://open.spotify.com/track/3K0Xr4N0ccBKqBBHDARIFy"
  },
  {
    "platform": "Spotify",
    "timestamp": "2025-09-24T03:07:53.455Z",
    "content": "Fujii Kaze の「Okay, Goodbye」を聴きました",
    "url": "https://open.spotify.com/track/1Vw0JiY6Jk8vCypHzb3fo4"
  },
  {
    "platform": "Spotify",
    "timestamp": "2025-09-24T03:03:24.635Z",
    "content": "Fujii Kaze の「You」を聴きました",
    "url": "https://open.spotify.com/track/2vQhYhGSBBamRhhJeWprr1"
  },
  {
    "platform": "Spotify",
    "timestamp": "2025-09-24T02:58:43.480Z",
    "content": "Fujii Kaze の「It Ain't Over」を聴きました",
    "url": "https://open.spotify.com/track/7xWKGIFGLxBJAyGSus7BOJ"
  },
  {
    "platform": "Spotify",
    "timestamp": "2025-09-24T02:53:43.455Z",
    "content": "Fujii Kaze の「Prema」を聴きました",
    "url": "https://open.spotify.com/track/0IByNT868RxZwmcj1rQgno"
  },
  {
    "platform": "Spotify",
    "timestamp": "2025-09-24T02:49:26.177Z",
    "content": "Fujii Kaze の「Love Like This」を聴きました",
    "url": "https://open.spotify.com/track/45uzEq3hAOy8uayrvDLY2C"
  },
  {
    "platform": "Spotify",
    "timestamp": "2025-09-24T02:44:59.659Z",
    "content": "Fujii Kaze の「Hachikō」を聴きました",
    "url": "https://open.spotify.com/track/3Aj0zsny1zlTLevRxfEEKc"
  },
  {
    "platform": "Spotify",
    "timestamp": "2025-09-24T02:40:29.285Z",
    "content": "Fujii Kaze の「I Need U Back」を聴きました",
    "url": "https://open.spotify.com/track/2D7Bqzfa2pJqa0LUftrVgx"
  },
  {
    "platform": "Spotify",
    "timestamp": "2025-09-24T02:37:22.903Z",
    "content": "Fujii Kaze の「Casket Girl」を聴きました",
    "url": "https://open.spotify.com/track/46LSraL1efyLHbM5DehGtN"
  }
]