[
  {
    "platform": "Spotify",
    "timestamp": "2026-02-12T12:46:30.209Z",
    "content": "Taeko Onuki の「何もいらない」を聴きました",
    "url": "https://open.spotify.com/track/2daDWlwE6JzDZZsjWlCUAC"
  },
  {
    "platform": "Spotify",
    "timestamp": "2026-02-12T09:29:17.673Z",
    "content": "Taeko Onuki の「くすりをたくさん」を聴きました",
    "url": "https://open.spotify.com/track/2eD6XNSxGGInddLRp1G7I5"
  },
  {
    "platform": "Spotify",
    "timestamp": "2026-02-12T09:23:37.797Z",
    "content": "Taeko Onuki の「幻惑」を聴きました",
    "url": "https://open.spotify.com/track/6s06bjGHrblBBtzQavQuZC"
  },
  {
    "platform": "Spotify",
    "timestamp": "2026-02-12T09:17:25.555Z",
    "content": "Taeko Onuki の「RECIPE ＜調理法＞」を聴きました",
    "url": "https://open.spotify.com/track/6RaesaYwzgLW87u4Oz9e5x"
  },
  {
    "platform": "Spotify",
    "timestamp": "2026-02-12T09:13:46.161Z",
    "content": "Taeko Onuki の「テディ・ベア」を聴きました",
    "url": "https://open.spotify.com/track/0166EsbC1BXp3i5WE8akIF"
  },
  {
    "platform": "Spotify",
    "timestamp": "2026-02-11T20:33:47.723Z",
    "content": "Aya Hirano の「止マレ!」を聴きました",
    "url": "https://open.spotify.com/track/2lOP2DlQiQWrN2rUK4CwPf"
  },
  {
    "platform": "Spotify",
    "timestamp": "2026-02-11T20:29:52.367Z",
    "content": "Aya Hirano の「Super Driver」を聴きました",
    "url": "https://open.spotify.com/track/44mbjuZCCG7yNHUAf5AyDv"
  },
  {
    "platform": "Spotify",
    "timestamp": "2026-02-11T20:25:34.251Z",
    "content": "Aya Hirano の「運命的事件の幸福」を聴きました",
    "url": "https://open.spotify.com/track/7Mi5xKqdrghEkACWf33Al0"
  },
  {
    "platform": "Spotify",
    "timestamp": "2026-02-11T20:21:03.496Z",
    "content": "Aya Hirano の「最強パレパレード」を聴きました",
    "url": "https://open.spotify.com/track/18k6gyOaqoLQJkrOtBI7Vx"
  },
  {
    "platform": "Spotify",
    "timestamp": "2026-02-11T20:16:44.752Z",
    "content": "Aya Hirano の「うぇるかむUNKNOWN」を聴きました",
    "url": "https://open.spotify.com/track/2I9qi4lug8VrFJShP744CK"
  }
]