[
  {
    "platform": "Spotify",
    "timestamp": "2026-02-18T18:19:48.845Z",
    "content": "Noriyuki Makihara の「もう恋なんてしない - 2012 Remaster」を聴きました",
    "url": "https://open.spotify.com/track/2GU85vhIa7EGUt5mDNLHK6"
  },
  {
    "platform": "Spotify",
    "timestamp": "2026-02-18T10:25:17.721Z",
    "content": "Takenobu Mitsuyoshi の「The King of Speed - Daytona USA Re;mix」を聴きました",
    "url": "https://open.spotify.com/track/7LqTzGkH8CzOXLVpsoC3LZ"
  },
  {
    "platform": "Spotify",
    "timestamp": "2026-02-17T20:00:53.011Z",
    "content": "SEGA SOUND TEAM の「OPENING JINGLE (OutRun2 series)」を聴きました",
    "url": "https://open.spotify.com/track/1M59C83uyJeEGOzcZYg79H"
  },
  {
    "platform": "Spotify",
    "timestamp": "2026-02-17T19:47:28.168Z",
    "content": "DE DE MOUSE の「charmed」を聴きました",
    "url": "https://open.spotify.com/track/0NRD9BUB1E1py9d5WhZuSL"
  },
  {
    "platform": "Spotify",
    "timestamp": "2026-02-17T19:43:26.889Z",
    "content": "DE DE MOUSE の「love destination」を聴きました",
    "url": "https://open.spotify.com/track/2MRijdxTKflv4EU9EtsShK"
  },
  {
    "platform": "Spotify",
    "timestamp": "2026-02-17T19:39:11.873Z",
    "content": "DE DE MOUSE の「be yourself」を聴きました",
    "url": "https://open.spotify.com/track/2xmM54W5qketGHgLilzynh"
  },
  {
    "platform": "Spotify",
    "timestamp": "2026-02-17T19:34:42.237Z",
    "content": "BIM の「RASEN」を聴きました",
    "url": "https://open.spotify.com/track/7Ioe77iVs0S1enZ2X9nOUF"
  },
  {
    "platform": "Spotify",
    "timestamp": "2026-02-17T19:03:23.962Z",
    "content": "RHYMESTER の「午前零時 -Intro」を聴きました",
    "url": "https://open.spotify.com/track/20ge8zv2utvkIl1z0UPIen"
  },
  {
    "platform": "Spotify",
    "timestamp": "2026-02-17T14:00:17.092Z",
    "content": "Perfume の「チョコレイト・ディスコ」を聴きました",
    "url": "https://open.spotify.com/track/35WLGytCEIVPLBPfhNPhTp"
  },
  {
    "platform": "Spotify",
    "timestamp": "2026-02-17T13:52:27.740Z",
    "content": "Sheena Ringo の「おだいじに」を聴きました",
    "url": "https://open.spotify.com/track/52UchVYXQRUsIgGptAA9Wa"
  }
]