[
  {
    "platform": "Spotify",
    "timestamp": "2026-02-13T19:21:00.897Z",
    "content": "モーニング娘。'17 の「ジェラシー ジェラシー」を聴きました",
    "url": "https://open.spotify.com/track/1H3IEUCcmSqhBh7rgJvG5I"
  },
  {
    "platform": "Spotify",
    "timestamp": "2026-02-13T19:16:31.171Z",
    "content": "モーニング娘。'17 の「BRAND NEW MORNING」を聴きました",
    "url": "https://open.spotify.com/track/2nbXgGhSTngP6sz6HHlAEI"
  },
  {
    "platform": "Spotify",
    "timestamp": "2026-02-13T19:12:03.856Z",
    "content": "モーニング娘。'16 の「そうじゃない」を聴きました",
    "url": "https://open.spotify.com/track/7B4OeilrH8iSIwgYdPXgxs"
  },
  {
    "platform": "Spotify",
    "timestamp": "2026-02-13T19:07:30.999Z",
    "content": "モーニング娘。'16 の「ムキダシで向き合って」を聴きました",
    "url": "https://open.spotify.com/track/4waLjqjU3VtUfbDS47IVAI"
  },
  {
    "platform": "Spotify",
    "timestamp": "2026-02-13T19:03:32.027Z",
    "content": "モーニング娘。'16 の「セクシーキャットの演説」を聴きました",
    "url": "https://open.spotify.com/track/0rldGrYoChr83vSgfk2SS8"
  },
  {
    "platform": "Spotify",
    "timestamp": "2026-02-13T18:58:31.697Z",
    "content": "モーニング娘。'16 の「Tokyoという片隅」を聴きました",
    "url": "https://open.spotify.com/track/4Su8LqzOzky2Hz7FnF7WoW"
  },
  {
    "platform": "Spotify",
    "timestamp": "2026-02-13T18:54:02.448Z",
    "content": "モーニング娘。'16 の「The Vision」を聴きました",
    "url": "https://open.spotify.com/track/5Q1cOJKUU8zeDrhLdyRWua"
  },
  {
    "platform": "Spotify",
    "timestamp": "2026-02-13T18:48:31.378Z",
    "content": "モーニング娘。'16 の「泡沫サタデーナイト！」を聴きました",
    "url": "https://open.spotify.com/track/2guwsLLGdI5AYvlMMjeTyC"
  },
  {
    "platform": "Spotify",
    "timestamp": "2026-02-13T18:12:49.059Z",
    "content": "Soutaiseiriron の「上海an」を聴きました",
    "url": "https://open.spotify.com/track/0vsRDMLOSopWyNJdiAgq5v"
  },
  {
    "platform": "Spotify",
    "timestamp": "2026-02-13T18:12:39.509Z",
    "content": "モーニング娘。 の「恋のダイヤル6700」を聴きました",
    "url": "https://open.spotify.com/track/26ZvtpFiZOQPFJ5KEuloys"
  }
]